{
 "lives": [
     {
     "name": "🍋┃Jack港台",
     "type":0,
     "url":"https://smart.946985.filegear-sg.me/sub.php?user=tgyoyo82520",
     "ua":"goiptv/8.8.8",
     "timeout": 10,
     "playerType": 2
     },
     {
      "name": "🍏┃日后港澳",
      "type": 0,
      "url": "http://rihou.cc:555/gggg.nzk",
      "playerType": 2,
      "ua": "okhttp/3.15",
      "timeout": 10
     },
      {
      "name": "🥭┃港台大陆",
      "url":"https://gh-proxy.org/https://raw.githubusercontent.com/FGBLH/FG/refs/heads/main/港台大陆无18内容",
      "playerType": 2,
      "ua": "",
      "timeout": 10
    },
      {
      "name": "🥎┃易发直播",
      "type": 0,
      "url": "https://gh-proxy.org/https://raw.githubusercontent.com/fafa002/yf2025/refs/heads/main/yiyifafa.txt",
      "ua": "okHttp",
      "playerType": 2,
      "timeout": 10
     },
      {
      "name": "🏀┃AI直播",
      "type": 0,
      "url": "http://127.0.0.1:9978/proxy?do=live&url=https://ds65.tv1288.xyz",
      "playerType": 2,
      "timeout": 10
      },
       {
       "name": "🍊┃台灣直播",
       "type": 0,
       "ua": "okhttp",
       "url": "https://iptv.852851.xyz/sub/K5hMyUOy52A1rzUvV6s5pbADasExbi7x/playlist.m3u",
       "timeout": 10,
       "playerType": 2
     },
     {
     "name": "🎞️┃Jack直播",
     "type":0,
     "url":"https://php.946985.filegear-sg.me/jackTV.m3u",
     "ua":"goiptv/8.8.8",
     "timeout": 10,
     "playerType": 2
     },
     {
      "name": "🏉┃Jack港澳",
      "type": 0,
      "url":"https://iptv.852851.xyz/sub/K5hMyUOy52A1rzUvV6s5pbADasExbi7x/playlist.m3u",
      "ua":"goiptv/8.8.8",
      "playerType": 2,
      "timeout": 10
     },
      {
      "name": "🍎┃Jack电视",
      "type": 0,
      "ua":"goiptv/8.8.8",
      "url": "https://php.946985.filegear-sg.me/test.m3u"
     },
    {
    	"name": "🐰┃港澳直播",
      "type": 0,
      "url":"https://iptv.yang-1989.eu.org/m3u/myTV.m3u",
      "playerType": 2,
      "ua": "okhttp/3.8.1",
      "timeout": 10
     },
     {
     "name": "🍍┃电视直播",
     "type":0,
     "url": "https://iptv.yang-1989.eu.org/m3u/Gather.m3u",
     "ua": "okhttp/3.8.1",
     "timeout": 10,
     "playerType": 2
     },

    {
      "name": "🏐┃港澳台🔞",
      "url":"https://gh-proxy.org/https://raw.githubusercontent.com/FGBLH/FG/refs/heads/main/%E6%B8%AF%E5%8F%B0%E5%A4%A7%E9%99%86",
      "playerType": 2,
      "ua": "",
      "timeout": 10
    },
     {
      "name": "🍋┃新时代🔞",
      "url":"https://gh-proxy.org/https://raw.githubusercontent.com/FGBLH/FG/refs/heads/main/%E5%AE%89%E5%8D%9A",
      "playerType": 2,
      "ua": "",
      "timeout": 10
    },
    {
      "name": "🍓┃亚麻蝶🔞",
      "type": 0,
      "ua": "okhttp",
      "url": "https://xoxo.cn.mt/Lonely.m3u"
     }, 
      {
      "name": "🍑┃视频蝶🔞",
      "url":"https://gh-proxy.org/https://raw.githubusercontent.com/FGBLH/FG/refs/heads/main/xxx%E8%A7%86%E9%A2%91%E8%B5%84%E6%BA%90",
      "playerType": 2,
      "ua": "",
      "timeout": 10
    },
    {
      "name": "🍇┃裤佬直播",
      "type": 0,
      "url": "https://gh-proxy.org/https://raw.githubusercontent.com/Jsnzkpg/Jsnzkpg/Jsnzkpg/Jsnzkpg1.m3u",
      "playerType": 2,
      "timeout": 10,
      "ua": "okHttp"   
    }
  ]
}
